blownotes/__init__.py
blownotes/__main__.py
blownotes/rms_mode.py
blownotes/split_mode.py
blownotes-0.1.2.dist-info/licenses/LICENSE
blownotes-0.1.2.dist-info/METADATA
blownotes-0.1.2.dist-info/WHEEL
blownotes-0.1.2.dist-info/entry_points.txt
blownotes-0.1.2.dist-info/top_level.txt
blownotes-0.1.2.dist-info/RECORD
