Metadata-Version: 2.4
Name: blownotes
Version: 0.1.2
Summary: Extraia notas dominantes de um áudio (.wav, .mp3, etc) com precisão RMS ou por regiões ativas.
Author-email: "I. Zanoth" <ivanzanoth@gmail.com>
License: MIT
Project-URL: Homepage, https://zanoth.vercel.app
License-File: LICENSE
Requires-Dist: librosa
Requires-Dist: numpy
Dynamic: license-file
